robingrad/__init__.py
robingrad/graph.py
robingrad/lab.py
robingrad/optim.py
robingrad/state.py
robingrad/tensor.py
robingrad/nn/__init__.py
robingrad/nn/loss.py
robingrad-0.1.0.dist-info/LICENSE
robingrad-0.1.0.dist-info/METADATA
robingrad-0.1.0.dist-info/WHEEL
robingrad-0.1.0.dist-info/top_level.txt
robingrad-0.1.0.dist-info/RECORD
