Metadata-Version: 2.1
Name: robingrad
Version: 0.1.0
Summary: Something between Tinygrad and Micrograd
Author-email: Marco Salvalaggio <mar.salvalaggio@gmail.com>
License: Copyright (c) 2023 Marco Salvalaggio
Project-URL: Homepage, https://github.com/marcosalvalaggio/robingrad
Project-URL: Bug Tracker, https://github.com/marcosalvalaggio/robingrad/issues
Classifier: Programming Language :: Python :: 3
Classifier: License :: OSI Approved :: MIT License
Classifier: Operating System :: OS Independent
Requires-Python: >=3.7
License-File: LICENSE
Requires-Dist: graphviz
Requires-Dist: numpy
